openagents/__init__.py
openagents/cli.py
openagents/agents/base.py
openagents/agents/runner.py
openagents/agents/simple_openai_agent.py
openagents/core/__init__.py
openagents/core/base_protocol.py
openagents/core/base_protocol_adapter.py
openagents/core/client.py
openagents/core/connector.py
openagents/core/network.py
openagents/core/system_commands.py
openagents/launchers/__init__.py
openagents/launchers/discovery_connector.py
openagents/launchers/network_launcher.py
openagents/launchers/terminal_console.py
openagents/models/__init__.py
openagents/models/manifest.py
openagents/models/message_thread.py
openagents/models/messages.py
openagents/models/network_config.py
openagents/models/network_profile.py
openagents/models/tool.py
openagents/protocols/__init__.py
openagents/protocols/communication/__init__.py
openagents/protocols/communication/simple_messaging/__init__.py
openagents/protocols/communication/simple_messaging/adapter.py
openagents/protocols/communication/simple_messaging/protocol.py
openagents/protocols/discovery/__init__.py
openagents/protocols/discovery/agent_discovery/__init__.py
openagents/protocols/discovery/agent_discovery/adapter.py
openagents/protocols/discovery/agent_discovery/protocol.py
openagents/utils/__init__.py
openagents/utils/message_util.py
openagents/utils/network_discovey.py
openagents/utils/protocol_loaders.py
omniagents-0.4.0.dist-info/LICENSE
omniagents-0.4.0.dist-info/METADATA
omniagents-0.4.0.dist-info/WHEEL
omniagents-0.4.0.dist-info/entry_points.txt
omniagents-0.4.0.dist-info/top_level.txt
omniagents-0.4.0.dist-info/RECORD
